glucose360/__init__.py
glucose360/config.ini
glucose360/event_colors.json
glucose360/events.py
glucose360/features.py
glucose360/main.py
glucose360/plots.py
glucose360/preprocessing.py
glucose360-0.0.2.dist-info/licenses/LICENSE
glucose360-0.0.2.dist-info/METADATA
glucose360-0.0.2.dist-info/WHEEL
glucose360-0.0.2.dist-info/top_level.txt
glucose360-0.0.2.dist-info/RECORD
