Metadata-Version: 2.4
Name: glucose360
Version: 0.0.2
Summary: Python package by Stanford University's Snyder Lab for holistic continuous glucose monitoring (CGM) analysis for both patients and researchers.
Author-email: Dhruv Aron <dhruv.aron@gmail.com>, "Ben W. Ehlert" <behlert@stanford.edu>
Project-URL: Homepage, https://github.com/vurhd2/Python-CGM-Package
Project-URL: Issues, https://github.com/vurhd2/Python-CGM-Package/issues
Classifier: Programming Language :: Python :: 3
Classifier: License :: OSI Approved :: GNU General Public License v2 (GPLv2)
Classifier: Operating System :: OS Independent
Requires-Python: >=3.11
License-File: LICENSE
Dynamic: license-file
